shakecore/__init__.py
shakecore/beamforming/__init__.py
shakecore/beamforming/beamforming.py
shakecore/clients/__init__.py
shakecore/clients/https/__init__.py
shakecore/clients/https/client.py
shakecore/conv/__init__.py
shakecore/conv/backup/convert.py
shakecore/conv/das.py
shakecore/conv/hydrophone.py
shakecore/conv/map.py
shakecore/core/__init__.py
shakecore/core/manipulation/__init__.py
shakecore/core/manipulation/manipulation_pool.py
shakecore/core/manipulation/manipulation_stream.py
shakecore/core/operator/__init__.py
shakecore/core/operator/operator_pool.py
shakecore/core/operator/operator_stream.py
shakecore/core/pool.py
shakecore/core/stats.py
shakecore/core/stream.py
shakecore/core/utils.py
shakecore/io/__init__.py
shakecore/io/read.py
shakecore/io/sc/__init__.py
shakecore/io/sc/core.py
shakecore/io/silixah5/__init__.py
shakecore/io/silixah5/core.py
shakecore/io/tdms/__init__.py
shakecore/io/tdms/core.py
shakecore/io/terra15/__init__.py
shakecore/io/terra15/core.py
shakecore/io/utils.py
shakecore/io/write.py
shakecore/picker/__init__.py
shakecore/polarization/__init__.py
shakecore/ppsd/__init__.py
shakecore/ppsd/backup/ppsd.py
shakecore/ppsd/ppsd.py
shakecore/setting.py
shakecore/signal/__init__.py
shakecore/signal/decimate.py
shakecore/signal/denoise/__init__.py
shakecore/signal/denoise/afk.py
shakecore/signal/denoise/basic_filter.py
shakecore/signal/denoise/curvelet.py
shakecore/signal/denoise/fk.py
shakecore/signal/denoise/radon.py
shakecore/signal/detrend.py
shakecore/signal/differentiate.py
shakecore/signal/filter.py
shakecore/signal/integrate.py
shakecore/signal/interpolate.py
shakecore/signal/mute.py
shakecore/signal/remove_response.py
shakecore/signal/resample.py
shakecore/signal/rotate.py
shakecore/signal/stack.py
shakecore/signal/statistics.py
shakecore/signal/taper.py
shakecore/sov/__init__.py
shakecore/sov/sov.py
shakecore/tests/__init__.py
shakecore/tests/test_clients/__init__.py
shakecore/tests/test_clients/test_main.py
shakecore-0.0.5.dist-info/LICENSE
shakecore-0.0.5.dist-info/METADATA
shakecore-0.0.5.dist-info/WHEEL
shakecore-0.0.5.dist-info/RECORD
